2014-2015-1.bundesliga.ics
2014-2015-2.bundesliga-nord.ics
2014-2015-landesliga-brandenburg.ics
2014-2015-turbine-potsdam.ics
CHANGES.md
Makefile
README.md
fblics.py
setup.py
fblics.egg-info/PKG-INFO
fblics.egg-info/SOURCES.txt
fblics.egg-info/dependency_links.txt
fblics.egg-info/entry_points.txt
fblics.egg-info/not-zip-safe
fblics.egg-info/requires.txt
fblics.egg-info/top_level.txt