Metadata-Version: 1.1
Name: fblics
Version: v1
Summary: convert Frauen-Bundesliga schedule to iCalendar data exchange format
Home-page: https://github.com/witsch/fblics
Author: Andreas Zeidler
Author-email: az at zitc.de
License: UNKNOWN
Platform: UNKNOWN
Classifier: Programming Language :: Python
